yutto/__init__.py
yutto/__main__.py
yutto/__version__.py
yutto/_typing.py
yutto/download_manager.py
yutto/exceptions.py
yutto/mcp.py
yutto/parser.py
yutto/path_resolver.py
yutto/py.typed
yutto/validator.py
yutto/api/__init__.py
yutto/api/bangumi.py
yutto/api/cheese.py
yutto/api/collection.py
yutto/api/danmaku.py
yutto/api/space.py
yutto/api/ugc_video.py
yutto/api/user_info.py
yutto/bilibili_typing/__init__.py
yutto/bilibili_typing/codec.py
yutto/bilibili_typing/quality.py
yutto/cli/__init__.py
yutto/cli/cli.py
yutto/cli/settings.py
yutto/downloader/__init__.py
yutto/downloader/downloader.py
yutto/downloader/progressbar.py
yutto/downloader/selector.py
yutto/extractor/__init__.py
yutto/extractor/_abc.py
yutto/extractor/bangumi.py
yutto/extractor/bangumi_batch.py
yutto/extractor/cheese.py
yutto/extractor/cheese_batch.py
yutto/extractor/collection.py
yutto/extractor/common.py
yutto/extractor/favourites.py
yutto/extractor/series.py
yutto/extractor/ugc_video.py
yutto/extractor/ugc_video_batch.py
yutto/extractor/user_all_favourites.py
yutto/extractor/user_all_ugc_videos.py
yutto/extractor/user_watch_later.py
yutto/utils/__init__.py
yutto/utils/asynclib.py
yutto/utils/danmaku.py
yutto/utils/fetcher.py
yutto/utils/ffmpeg.py
yutto/utils/file_buffer.py
yutto/utils/filter.py
yutto/utils/metadata.py
yutto/utils/priority.py
yutto/utils/subtitle.py
yutto/utils/time.py
yutto/utils/console/__init__.py
yutto/utils/console/attributes.py
yutto/utils/console/colorful.py
yutto/utils/console/formatter.py
yutto/utils/console/logger.py
yutto/utils/console/status_bar.py
yutto/utils/funcutils/__init__.py
yutto/utils/funcutils/aobject.py
yutto/utils/funcutils/as_sync.py
yutto/utils/funcutils/data_access.py
yutto/utils/funcutils/filter_none_value.py
yutto/utils/funcutils/functional.py
yutto/utils/funcutils/singleton.py
yutto/utils/funcutils/xmerge.py
uiya_yutto-0.0.1.dist-info/METADATA
uiya_yutto-0.0.1.dist-info/WHEEL
uiya_yutto-0.0.1.dist-info/entry_points.txt
uiya_yutto-0.0.1.dist-info/licenses/LICENSE
uiya_yutto-0.0.1.dist-info/RECORD
