Metadata-Version: 2.4
Name: uiya-yutto
Version: 0.0.1
Summary: 🧊 一个可爱且任性的 B 站视频下载器
Project-URL: Homepage, https://github.com/yutto-dev/yutto
Project-URL: Documentation, https://github.com/yutto-dev/yutto
Project-URL: Repository, https://github.com/yutto-dev/yutto
Project-URL: Issues, https://github.com/yutto-dev/yutto/issues
Author-email: Nyakku Shigure <sigure.qaq@gmail.com>, XnneHang <xnnehang@gmail.com>
License: GPL-3.0
License-File: LICENSE
Keywords: bilibili,danmaku,downloader,python,video
Classifier: Environment :: Console
Classifier: License :: OSI Approved :: GNU General Public License v3 (GPLv3)
Classifier: Operating System :: OS Independent
Classifier: Programming Language :: Python
Classifier: Programming Language :: Python :: 3
Classifier: Programming Language :: Python :: 3.10
Classifier: Programming Language :: Python :: 3.11
Classifier: Programming Language :: Python :: 3.12
Classifier: Programming Language :: Python :: 3.13
Classifier: Programming Language :: Python :: Implementation :: CPython
Classifier: Typing :: Typed
Requires-Python: >=3.10
Requires-Dist: aiofiles>=24.1.0
Requires-Dist: biliass==2.2.2
Requires-Dist: colorama>=0.4.6; sys_platform == 'win32'
Requires-Dist: dict2xml>=1.7.6
Requires-Dist: httpx[http2,socks]>=0.28.1
Requires-Dist: pydantic>=2.11.2
Requires-Dist: returns>=0.25.0
Requires-Dist: tomli>=2.0.2; python_version < '3.11'
Requires-Dist: typing-extensions>=4.13.1
Provides-Extra: mcp
Requires-Dist: mcp[cli]>=1.6.0; extra == 'mcp'
